{
    "здр" : "здраво",
    "Здр" : "Здраво",
    "дек" : "каде",
    "Дек" : "Каде",
    "ела" : "дојди",
    "Ела" : "Дојди",
    "итн" : "и така натаму",
    "Итн" : "И така натаму",
    "кец" : "единица",
    "Кец" : "Единица",
    "бус" : "автобус",
    "Бус" : "Автобус",
    "кола" : "автомобил",
    "Кола" : "Автомобил",
    "тел" : "телефон",
    "Тел" : "Телефон",
    "моб" : "мобилен",
    "Моб" : "Мобилен",
    "пошто" : "затоа што",
    "Пошто" : "Затоа што",
    "оти" : "зошто",
    "Оти" : "Зошто",
    "мн" : "многу",
    "Мн" : "Многу",
    "м'гла" : "магла",
    "М'гла" : "Магла",
    "с'нце" : "сонце",
    "С'нце" : "Сонце",
    "дал" : "дали",
    "Дал" : "Дали",
    "зш" : "зошто",
    "Зш" : "Зошто",
    "так" : "така",
    "Так" : "Така",
    "кд" : "кога",
    "Кд" : "Кога",
    "как" : "како",
    "Как" : "Како",
    "тг" : "тогаш",
    "Тг" : "Тогаш",
    "к'д" : "кога",
    "К'д" : "Кога",
    "т'г" : "тогаш",
    "Т'г" : "Тогаш",
    "тогај" : "тогаш",
    "Тогај" : "Тогаш",
    "превземе" : "преземе",
    "Превземе" : "Преземе",
    "сеуште" : "сѐ уште",
    "Сеуште" : "Сѐ уште",
    "се уште" : "сѐ уште",
    "Се уште" : "Сѐ уште",
    "можит" : "може",
    "Можит" : "Може",
    "двојче" : "двојка",
    "Двојче" : "Двојка",
    "мома" : "девојка",
    "Мома" : "Девојка",
    "одит" : "оди",
    "Одит" : "Оди",
    "ден" : "денар",
    "Ден" : "Денар",
    "мож" : "можеби",
    "Мож" : "Можеби",
    "едну" : "една",
    "Едну" : "Една",
    "али" : "но",
    "Али" : "но",
    "водит" : "води",
    "Водит" : "Води",
    "снајдиш" : "снајде",
    "Снајдиш" : "Снајде",
    "мојто" : "моето",
    "Мојто" : "Моето",
    "твојто" : "твоето",
    "Твојто" : "Твоето",
    "знајш" : "знаеш",
    "Знајш" : "Знаеш",
    "поз" : "поздрав",
    "Поз" : "Поздрав",
    "позз" : "поздрав",
    "Позз" : "Поздрав",
    "ок" : "океј",
    "Ок" : "Океј",
    "ОК" : "Океј",
    "У" : "Во",
    "у" : "во",
    "ваљда" : "најверојатно",
    "Ваљда" : "Најверојатно",
    "можда" : "можеби",
    "Можда" : "Можеби",
    "преко" : "преку",
    "Преко" : "Преку",
    "важит" : "важи",
    "Важит" : "Важи",
    "слнце" : "сонце",
    "Слнце" : "Сонце",
    "Сга" : "Сега",
    "сга" : "сега"
}
